[
    {
        "id": "breakfast-1",
        "number": 1,
        "type": "Breakfast",
        "name": "Breakfast 1",
        "image": "src\\assets\\Picture.jpg",
        "ingredients": ["one", "two", "three"],
        "howTo": "How to make ............................. ............................. ............................. ............................. ............................. ............................. ............................. ............................. ............................. ............................. ............................. ............................. ............................. ............................. ............................."
    },
    {
        "id": "breakfast-2",
        "number": 2,
        "type": "Breakfast",
        "name": "Breakfast 2",
        "image": "src\\assets\\Picture.jpg",
        "ingredients": ["one", "two", "three"],
        "howTo": "How to make ............................. ............................. ............................. ............................. ............................. ............................. ............................. ............................. ............................. ............................. ............................. ............................. ............................. ............................. ............................."
    },
    {
        "id": "breakfast-3",
        "number": 3,
        "type": "Breakfast",
        "name": "Breakfast 3",
        "image": "src\\assets\\Picture.jpg",
        "ingredients": ["one", "two", "three"],
        "howTo": "How to make ............................. ............................. ............................. ............................. ............................. ............................. ............................. ............................. ............................. ............................. ............................. ............................. ............................. ............................. ............................."
    },
    {
        "id": "breakfast-4",
        "number": 4,
        "type": "Breakfast",
        "name": "Breakfast 1",
        "image": "src\\assets\\Picture.jpg",
        "ingredients": ["one", "two", "three"],
        "howTo": "How to make ............................. ............................. ............................. ............................. ............................. ............................. ............................. ............................. ............................. ............................. ............................. ............................. ............................. ............................. ............................."
    },
    {
        "id": "breakfast-5",
        "number": 5,
        "type": "Breakfast",
        "name": "Breakfast 2",
        "image": "src\\assets\\Picture.jpg",
        "ingredients": ["one", "two", "three"],
        "howTo": "How to make ............................. ............................. ............................. ............................. ............................. ............................. ............................. ............................. ............................. ............................. ............................. ............................. ............................. ............................. ............................."
    },
    {
        "id": "breakfast-6",
        "number": 6,
        "type": "Breakfast",
        "name": "Breakfast 3",
        "image": "src\\assets\\Picture.jpg",
        "ingredients": ["one", "two", "three"],
        "howTo": "How to make ............................. ............................. ............................. ............................. ............................. ............................. ............................. ............................. ............................. ............................. ............................. ............................. ............................. ............................. ............................."
    },
    {
        "id": "breakfast-7",
        "number": 7,
        "type": "Breakfast",
        "name": "Breakfast 1",
        "image": "src\\assets\\Picture.jpg",
        "ingredients": ["one", "two", "three"],
        "howTo": "How to make ............................. ............................. ............................. ............................. ............................. ............................. ............................. ............................. ............................. ............................. ............................. ............................. ............................. ............................. ............................."
    },
    {
        "id": "breakfast-8",
        "number": 8,
        "type": "Breakfast",
        "name": "Breakfast 2",
        "image": "src\\assets\\Picture.jpg",
        "ingredients": ["one", "two", "three"],
        "howTo": "How to make ............................. ............................. ............................. ............................. ............................. ............................. ............................. ............................. ............................. ............................. ............................. ............................. ............................. ............................. ............................."
    },
    {
        "id": "breakfast-9",
        "number": 9,
        "type": "Breakfast",
        "name": "Breakfast 3",
        "image": "src\\assets\\Picture.jpg",
        "ingredients": ["one", "two", "three"],
        "howTo": "How to make ............................. ............................. ............................. ............................. ............................. ............................. ............................. ............................. ............................. ............................. ............................. ............................. ............................. ............................. ............................."
    },
    {
        "id": "breakfast-10",
        "number": 10,
        "type": "Breakfast",
        "name": "Breakfast 1",
        "image": "src\\assets\\Picture.jpg",
        "ingredients": ["one", "two", "three"],
        "howTo": "How to make ............................. ............................. ............................. ............................. ............................. ............................. ............................. ............................. ............................. ............................. ............................. ............................. ............................. ............................. ............................."
    },
    {
        "id": "breakfast-11",
        "number": 11,
        "type": "Breakfast",
        "name": "Breakfast 2",
        "image": "src\\assets\\Picture.jpg",
        "ingredients": ["one", "two", "three"],
        "howTo": "How to make ............................. ............................. ............................. ............................. ............................. ............................. ............................. ............................. ............................. ............................. ............................. ............................. ............................. ............................. ............................."
    },
    {
        "id": "breakfast-12",
        "number": 12,
        "type": "Breakfast",
        "name": "Breakfast 3",
        "image": "src\\assets\\Picture.jpg",
        "ingredients": ["one", "two", "three"],
        "howTo": "How to make ............................. ............................. ............................. ............................. ............................. ............................. ............................. ............................. ............................. ............................. ............................. ............................. ............................. ............................. ............................."
    }
]